{
    "ndk_module_path" :[
        "../../../../../cocos2d-x-3.9",
        "../../../../../cocos2d-x-3.9/cocos/",
        "../../../../../cocos2d-x-3.9/external",
        "../../../../../cocos2d-x-3.9/cocos/scripting"
    ],
    "copy_resources": [
        {
            "from": "../../../src",
            "to": "src"
        },
        {
            "from": "../../../res",
            "to": "res"
        }
    ],
    "must_copy_resources": [
        {
            "from": "../../../config.json",
            "to": ""
        }
    ]
}
